{"status": 200, "total": 15, "maxLimitPermitido": 100, "maxCantSucursalesPermitido": 50, "productos": [{"marca": "HUGGIES", "id": "7794626006098", "precioMax": 84.0, "precioMin": 76.65, "nombre": "Pan\u0303ales Talle Recien Nacido Mega Huggies x 20 Un", "presentacion": "20.0 un", "cantSucursalesDisponible": 16}, {"marca": "PAMPERS", "id": "7500435001113", "precioMax": 90.25, "precioMin": 79.0, "nombre": "Pan\u0303ales Talle Recien Nacido New Baby Pampers x 20 Un", "presentacion": "20.0 un", "cantSucursalesDisponible": 15}, {"marca": "PAMPERS", "id": "7506339398892", "precioMax": 65.9, "precioMin": 63.0, "nombre": "Pan\u0303ales Talle Recien Nacido Confort Sec Pampers x 20 Un", "presentacion": "20.0 un", "cantSucursalesDisponible": 10}, {"marca": "HUGGIES", "id": "7794626006128", "precioMax": 102.0, "precioMin": 96.3, "nombre": "Pan\u0303ales Talle Pequen\u0303o Recien Nacido Mega Huggies x 20 Un", "presentacion": "20.0 un", "cantSucursalesDisponible": 10}, {"marca": "HUGGIES", "id": "7794626006135", "precioMax": 178.0, "precioMin": 172.4, "nombre": "Pan\u0303ales Talle Pequen\u0303o Recien Nacido Hiper Huggies x 40 Un", "presentacion": "40.0 un", "cantSucursalesDisponible": 9}, {"marca": "PAMPERS", "id": "7506339398908", "precioMax": 131.35, "precioMin": 120.0, "nombre": "Pan\u0303ales Talle Recien Nacido Confort Sec Pampers x 40 Un", "presentacion": "40.0 un", "cantSucursalesDisponible": 8}, {"marca": "HUGGIES", "id": "7794626006418", "precioMax": 129.0, "precioMin": 70.5, "nombre": "Pan\u0303ales Talle Recien Nacido Active Sec Mega Huggies x 20 Un", "presentacion": "20.0 un", "cantSucursalesDisponible": 8}, {"marca": "HUGGIES", "id": "7794626006111", "precioMax": 61.0, "precioMin": 53.0, "nombre": "Pan\u0303ales Talle Pequen\u0303o Recien Nacido Huggies x 12 Un", "presentacion": "12.0 un", "cantSucursalesDisponible": 8}, {"marca": "HUGGIES", "id": "7794626006425", "precioMax": 155.0, "precioMin": 127.0, "nombre": "Pan\u0303ales Talle Recien Nacido Active Sec Hiper Huggies x 40 Un", "presentacion": "40.0 un", "cantSucursalesDisponible": 7}, {"marca": "PAMPERS", "id": "7500435001526", "precioMax": 159.0, "precioMin": 145.0, "nombre": "Pan\u0303ales Talle Recien Nacido New Baby Pampers x 40 Un", "presentacion": "40.0 un", "cantSucursalesDisponible": 7}, {"marca": "HUGGIES", "id": "7794626006104", "precioMax": 147.9, "precioMin": 145.0, "nombre": "Pan\u0303ales Talle Recien Nacido Hiper Huggies x 40 Un", "presentacion": "40.0 un", "cantSucursalesDisponible": 7}, {"marca": "HUGGIES", "id": "7794626007149", "precioMax": 110.0, "precioMin": 88.55, "nombre": "Pan\u0303ales Primeros 100 Dias Recien Nacido Premat Huggies x 30 Un", "presentacion": "30.0 un", "cantSucursalesDisponible": 6}, {"marca": "PAMPERS", "id": "7500435001120", "precioMax": 211.69, "precioMin": 149.0, "nombre": "Pan\u0303ales Talle Recien Nacido New Baby Pampers x 56 Un", "presentacion": "56.0 un", "cantSucursalesDisponible": 4}, {"marca": "PAMPERS", "id": "7506195100950", "precioMax": 147.9, "precioMin": 145.0, "nombre": "Pan\u0303ales Descartables Recien Nacido Pampers x 40 Un", "presentacion": "40.0 un", "cantSucursalesDisponible": 4}, {"marca": "PAMPERS", "id": "7506195100943", "precioMax": 44.0, "precioMin": 44.0, "nombre": "Pan\u0303ales Flex Recien Nacido Duo 0 Newborn Pampers x 20 Un", "presentacion": "20.0 un", "cantSucursalesDisponible": 3}], "totalPagina": 15}