{"status": 200, "total": 81, "maxLimitPermitido": 100, "maxCantSucursalesPermitido": 50, "productos": [{"marca": "ARCOR", "id": "7790580538002", "precioMax": 19.5, "precioMin": 19.0, "nombre": "Polenta Instantanea Prestopronta Arcor x 750 Gr", "presentacion": "750.0 gr", "cantSucursalesDisponible": 26}, {"marca": "PUREZA", "id": "7792180004512", "precioMax": 13.0, "precioMin": 8.49, "nombre": "Harina de Trigo 000 Pureza x 1 Kg.", "presentacion": "1.0 kg", "cantSucursalesDisponible": 22}, {"marca": "QUAKER", "id": "7792170007196", "precioMax": 16.0, "precioMin": 13.45, "nombre": "Polenta Instantanea Magica Quaker x 500 Gr", "presentacion": "500.0 gr", "cantSucursalesDisponible": 17}, {"marca": "BLANCAFLOR", "id": "7790070506924", "precioMax": 15.0, "precioMin": 13.5, "nombre": "Harina de Trigo 0000 Fortificada Blancaflor x 1.Kg", "presentacion": "1.0 kg", "cantSucursalesDisponible": 17}, {"marca": "PUREZA", "id": "7792180004871", "precioMax": 15.5, "precioMin": 13.74, "nombre": "Harina de Trigo 0000 Pureza x 1 Kg.", "presentacion": "1.0 kg", "cantSucursalesDisponible": 17}, {"marca": "DEL CAMPO", "id": "7798004720088", "precioMax": 9.9, "precioMin": 8.4, "nombre": "Polenta Instantanea Del Campo x 500 Gr", "presentacion": "500.0 gr", "cantSucursalesDisponible": 15}, {"marca": "FAVORITA", "id": "7790070507235", "precioMax": 9.6, "precioMin": 7.3, "nombre": "Harina de Trigo 000 con Vita Zinc Favorita x 1 Kg", "presentacion": "1.0 kg", "cantSucursalesDisponible": 15}, {"marca": "CA\u00d1UELAS", "id": "7792180001528", "precioMax": 7.08, "precioMin": 7.08, "nombre": "Harina de Trigo 000 Can\u0303uelas x 1 Kg", "presentacion": "1.0 kg", "cantSucursalesDisponible": 15}, {"marca": "BLANCAFLOR", "id": "7790070507228", "precioMax": 17.0, "precioMin": 15.5, "nombre": "Harina Leudante con Vita Zinc Blancaflor x 1 Kg", "presentacion": "1.0 kg", "cantSucursalesDisponible": 12}, {"marca": "PUREZA", "id": "7792180004888", "precioMax": 16.5, "precioMin": 12.48, "nombre": "Harina Leudante Pureza x 1 Kg", "presentacion": "1.0 kg", "cantSucursalesDisponible": 12}, {"marca": "PUREZA", "id": "7792180004567", "precioMax": 20.5, "precioMin": 15.0, "nombre": "Harina con Levadura Pizza Pureza x 1 Kg", "presentacion": "1.0 kg", "cantSucursalesDisponible": 12}, {"marca": "ARCOR", "id": "7790580660000", "precioMax": 19.35, "precioMin": 13.0, "nombre": "Polenta Instantanea Prestopronta Arcor x 500 Gr", "presentacion": "500.0 gr", "cantSucursalesDisponible": 10}, {"marca": "CARREFOUR", "id": "7798033332290", "precioMax": 14.0, "precioMin": 10.0, "nombre": "Polenta Carrefour x 1 Kg", "presentacion": "1.0 kg", "cantSucursalesDisponible": 10}, {"marca": "MAIZENA", "id": "7794000599185", "precioMax": 32.99, "precioMin": 29.49, "nombre": "Almidon de Maiz Maizena Bolsa x 520 Gr", "presentacion": "520.0 gr", "cantSucursalesDisponible": 10}, {"marca": "CARREFOUR", "id": "7798033339572", "precioMax": 12.0, "precioMin": 10.9, "nombre": "Polenta Instantanea Carrefour x 500 Gr", "presentacion": "500.0 gr", "cantSucursalesDisponible": 10}, {"marca": "DIA", "id": "8480017242730", "precioMax": 10.99, "precioMin": 10.99, "nombre": "Harina de Trigo 0000 Dia x 1 Kg", "presentacion": "1.0 kg", "cantSucursalesDisponible": 9}, {"marca": "DIA", "id": "8480017599988", "precioMax": 59.49, "precioMin": 58.59, "nombre": "Harina Maiz Tradicional Dia x 5 Kg", "presentacion": "5.0 kg", "cantSucursalesDisponible": 9}, {"marca": "DIA", "id": "8480017557674", "precioMax": 36.29, "precioMin": 36.29, "nombre": "Harina 000 Dia x 5 Kg", "presentacion": "5.0 kg", "cantSucursalesDisponible": 9}, {"marca": "DIA", "id": "8480017557438", "precioMax": 8.89, "precioMin": 8.89, "nombre": "Harina Maiz Rapida Dia x 500 Gr", "presentacion": "500.0 gr", "cantSucursalesDisponible": 9}, {"marca": "DIA", "id": "8480017557445", "precioMax": 12.79, "precioMin": 12.59, "nombre": "Harina de Maiz Dia x 1 Kg", "presentacion": "1.0 kg", "cantSucursalesDisponible": 9}, {"marca": "DIA", "id": "8480017242723", "precioMax": 7.59, "precioMin": 7.59, "nombre": "Harina de Trigo 000 Dia x 1 Kg", "presentacion": "1.0 kg", "cantSucursalesDisponible": 9}, {"marca": "RIVARA", "id": "7798004727070", "precioMax": 13.79, "precioMin": 13.59, "nombre": "Polenta Tradicional Rivara x 1 Kg", "presentacion": "1.0 kg", "cantSucursalesDisponible": 9}, {"marca": "CARREFOUR", "id": "7798159717261", "precioMax": 13.54, "precioMin": 6.1, "nombre": "Harina de Trigo 000 Carrefour x 1 Kg", "presentacion": "1.0 kg", "cantSucursalesDisponible": 9}, {"marca": "EGRAN", "id": "7791476025019", "precioMax": 19.0, "precioMin": 16.85, "nombre": "Polenta Egran x 1 Kg", "presentacion": "1.0 kg", "cantSucursalesDisponible": 8}, {"marca": "CASERITA", "id": "7792590000227", "precioMax": 12.99, "precioMin": 11.5, "nombre": "Harina de Trigo 0000 Caserita x 1 Kg", "presentacion": "1.0 kg", "cantSucursalesDisponible": 8}, {"marca": "CASERITA", "id": "7792590000159", "precioMax": 9.69, "precioMin": 7.89, "nombre": "Harina de Trigo 000 Caserita x 1 Kg", "presentacion": "1.0 kg", "cantSucursalesDisponible": 7}, {"marca": "EGRAN", "id": "7791476025002", "precioMax": 10.5, "precioMin": 8.55, "nombre": "Polenta Egran x 500 Gr", "presentacion": "500.0 gr", "cantSucursalesDisponible": 7}, {"marca": "PRESTOPRONTA", "id": "7790580660406", "precioMax": 18.0, "precioMin": 14.0, "nombre": "Polenta Instantanea con Hierro Prestopronta x 400 Gr", "presentacion": "400.0 gr", "cantSucursalesDisponible": 7}, {"marca": "PUREZA", "id": "7792180002563", "precioMax": 18.39, "precioMin": 18.29, "nombre": "Harina Pureza Integral x 1 Kg", "presentacion": "1.0 kg", "cantSucursalesDisponible": 6}, {"marca": "EGRAN", "id": "7791476022001", "precioMax": 11.1, "precioMin": 9.25, "nombre": "Polenta Instantanea Egran x 500 Gr", "presentacion": "500.0 gr", "cantSucursalesDisponible": 6}, {"marca": "PUREZA", "id": "7792180004901", "precioMax": 19.25, "precioMin": 15.0, "nombre": "Harina con Levadura Pan Pureza x 1 Kg", "presentacion": "1.0 kg", "cantSucursalesDisponible": 5}, {"marca": "B\u00c1RBARA", "id": "7794270000138", "precioMax": 9.19, "precioMin": 8.0, "nombre": "Polenta de Coccion Rapida Barbara x 0.50 Kg", "presentacion": "0.5 kg", "cantSucursalesDisponible": 3}, {"marca": "CARREFOUR", "id": "7798159717278", "precioMax": 14.11, "precioMin": 11.86, "nombre": "Harina Leudante Carrefour x 1 Kg", "presentacion": "1.0 kg", "cantSucursalesDisponible": 3}, {"marca": "CASERITA", "id": "7792590001156", "precioMax": 14.0, "precioMin": 14.0, "nombre": "Harina de Trigo para Pizzas Caserita x 1 Kg", "presentacion": "1.0 kg", "cantSucursalesDisponible": 3}, {"marca": "CASERITA", "id": "7792590001064", "precioMax": 14.0, "precioMin": 14.0, "nombre": "Harina Leudante Caserita x 1 Kg", "presentacion": "1.0 kg", "cantSucursalesDisponible": 3}, {"marca": "LUCCHETTI", "id": "7790070506665", "precioMax": 34.65, "precioMin": 34.65, "nombre": "Premezcla para Chipa Lucchetti Chipa x 0.25 Kg", "presentacion": "0.25 kg", "cantSucursalesDisponible": 2}, {"marca": "KAPAC", "id": "7794906000136", "precioMax": 62.99, "precioMin": 62.99, "nombre": "Premezcla Kapac para Pizza Libre de Gluten x 500 Gr", "presentacion": "500.0 gr", "cantSucursalesDisponible": 2}, {"marca": "CIUDAD DEL LAGO", "id": "12-1-2800001311567", "precioMax": 15.99, "precioMin": 15.99, "nombre": "Polenta Ciudad del Lago Bolsa x 1 Kg", "presentacion": "1.0 kg", "cantSucursalesDisponible": 2}, {"marca": "FAVORITA", "id": "7790070507259", "precioMax": 12.0, "precioMin": 11.5, "nombre": "Harina Leudante con Vita Zinc Favorita x 1 Kg", "presentacion": "1.0 kg", "cantSucursalesDisponible": 2}, {"marca": "KAPAC", "id": "7794906000242", "precioMax": 32.0, "precioMin": 32.0, "nombre": "Almidon de Maiz Kapac Libre de Gluten x 500 Gr", "presentacion": "500.0 gr", "cantSucursalesDisponible": 2}, {"marca": "FAVORITA", "id": "7790070507242", "precioMax": 16.39, "precioMin": 16.39, "nombre": "Harina Favorita 0000 Vitazink x 1 Kg", "presentacion": "1.0 kg", "cantSucursalesDisponible": 2}, {"marca": "KAPAC", "id": "7794906000143", "precioMax": 67.99, "precioMin": 67.99, "nombre": "Premezcla Kapac para N\u0303oquis Libre Gluten x 500 Gr", "presentacion": "500.0 gr", "cantSucursalesDisponible": 2}, {"marca": "VITINA", "id": "7790070318886", "precioMax": 15.49, "precioMin": 15.49, "nombre": "Semola Clasica Nueva Plus Lucchetti Vitina x 250 Gr", "presentacion": "250.0 gr", "cantSucursalesDisponible": 2}, {"marca": "MOLINO FAINAX", "id": "7798139291033", "precioMax": 22.99, "precioMin": 22.99, "nombre": "Harina para Faina Fainax Caja x 200 Gr", "presentacion": "200.0 gr", "cantSucursalesDisponible": 2}, {"marca": "CIUDAD DEL LAGO", "id": "12-1-2800001326349", "precioMax": 8.29, "precioMin": 8.29, "nombre": "Polenta Ciudad del Lago Bolsa x 500 Gr", "presentacion": "500.0 gr", "cantSucursalesDisponible": 2}, {"marca": "BRUNING", "id": "7791599000221", "precioMax": 9.49, "precioMin": 9.49, "nombre": "Harina Bruning Tipo 0000 x 1 Kg", "presentacion": "1.0 kg", "cantSucursalesDisponible": 2}, {"marca": "MOLINO CA\u00d1UELAS", "id": "7792180004864", "precioMax": 21.99, "precioMin": 21.99, "nombre": "Crepes Mama Cocina Plus Manzana x 300 Gr", "presentacion": "300.0 gr", "cantSucursalesDisponible": 2}, {"marca": "BARBARA", "id": "7794270000534", "precioMax": 14.49, "precioMin": 14.49, "nombre": "Premezcla Bizcochuelo Barbara Limon Barbara Limon x 450 Gr", "presentacion": "450.0 gr", "cantSucursalesDisponible": 2}, {"marca": "MOLINO CA\u00d1UELAS", "id": "7792180004840", "precioMax": 25.99, "precioMin": 25.99, "nombre": "Croquetas Mama Cocina Plus Espinaca x 300 Gr", "presentacion": "300.0 gr", "cantSucursalesDisponible": 2}, {"marca": "MAMA COCINA PLUS", "id": "7792180004833", "precioMax": 19.99, "precioMin": 19.99, "nombre": "Pizza Clasica Mama Cocina Plus x 500 Gr", "presentacion": "500.0 gr", "cantSucursalesDisponible": 2}, {"marca": "MAMA COCINA", "id": "7792180006776", "precioMax": 26.99, "precioMin": 26.99, "nombre": "Premezc N\u0303oquis Calab M Co", "presentacion": "400.0 gr", "cantSucursalesDisponible": 2}, {"marca": "PUREZA", "id": "7792180005113", "precioMax": 21.99, "precioMin": 21.99, "nombre": "Premezcla Pureza Pizza con Levadura x 550 Gr", "presentacion": "550.0 gr", "cantSucursalesDisponible": 2}, {"marca": "EGRAN", "id": "7791476019001", "precioMax": 26.99, "precioMin": 26.99, "nombre": "Almidon Egran de Maiz x 500 Gr", "presentacion": "500.0 gr", "cantSucursalesDisponible": 2}, {"marca": "COTO", "id": "12-1-2800002552136", "precioMax": 9.99, "precioMin": 9.99, "nombre": "Polenta Super Rapida Coto Paq 500 Grm", "presentacion": "500.0 gr", "cantSucursalesDisponible": 2}, {"marca": "LUCCHETTI", "id": "7790070506641", "precioMax": 21.49, "precioMin": 21.49, "nombre": "Premezcla para Pizza Lucchetti Pizza x 0.50 Kg", "presentacion": "0.5 kg", "cantSucursalesDisponible": 2}, {"marca": "EGRAN", "id": "7791476019025", "precioMax": 10.99, "precioMin": 10.99, "nombre": "Almidon Egran de Maiz x 200 Gr", "presentacion": "200.0 gr", "cantSucursalesDisponible": 2}, {"marca": "DEL CAMPO", "id": "7798004720071", "precioMax": 16.49, "precioMin": 16.49, "nombre": "Harina de Maiz Coccion Rapida Organica Del Campo x 500 Gr", "presentacion": "500.0 gr", "cantSucursalesDisponible": 2}, {"marca": "MAMA COCINA", "id": "7792180005632", "precioMax": 32.99, "precioMin": 32.99, "nombre": "Chipa Mama Cocina Plus x 250 Gr", "presentacion": "250.0 gr", "cantSucursalesDisponible": 2}, {"marca": "PUREZA", "id": "7792180005120", "precioMax": 21.99, "precioMin": 21.99, "nombre": "Premezcla Pureza Pizza Integral con Levadura x 550 Gr", "presentacion": "550.0 gr", "cantSucursalesDisponible": 2}, {"marca": "FERRERO", "id": "3223920720125", "precioMax": 159.99, "precioMin": 159.99, "nombre": "Harina Cous Cous Ferrero Precocida Est x 500 Gr", "presentacion": "500.0 gr", "cantSucursalesDisponible": 2}, {"marca": "FAINALIND", "id": "7791477000015", "precioMax": 23.99, "precioMin": 23.99, "nombre": "Harina de Garbanzo Fainalind Sobre x 200 Gr", "presentacion": "200.0 gr", "cantSucursalesDisponible": 2}, {"marca": "MOLINO CA\u00d1UELAS", "id": "7792180004857", "precioMax": 21.99, "precioMin": 21.99, "nombre": "Crepes Mama Cocina Plus Vainilla x 300 Gr", "presentacion": "300.0 gr", "cantSucursalesDisponible": 2}, {"marca": "LUCCHETTI", "id": "7790070508058", "precioMax": 21.99, "precioMin": 21.99, "nombre": "Premezcla Lucchetti Torta Frita x 0.51 Kg", "presentacion": "0.51 kg", "cantSucursalesDisponible": 2}, {"marca": "CARREFOUR", "id": "7798159717254", "precioMax": 14.24, "precioMin": 13.86, "nombre": "Harina de Trigo 0000 Carrefour x 1 Kg", "presentacion": "1.0 kg", "cantSucursalesDisponible": 2}, {"marca": "VITINA", "id": "7790070318879", "precioMax": 26.99, "precioMin": 26.99, "nombre": "Semola Clasica Fuente de Calcio Lucchetti Vitina x 0.54 Kg", "presentacion": "0.54 kg", "cantSucursalesDisponible": 2}, {"marca": "LUCCHETTI", "id": "7790070506658", "precioMax": 26.45, "precioMin": 26.45, "nombre": "Premezcla para N\u0303oquis Lucchetti N\u0303oquis x 0.40 Kg", "presentacion": "0.4 gr", "cantSucursalesDisponible": 2}, {"marca": "DEL CAMPO", "id": "7798004720026", "precioMax": 10.9, "precioMin": 10.9, "nombre": "Harina de Maiz de Campo Fortificada Rivara x 400 Gr", "presentacion": "400.0 gr", "cantSucursalesDisponible": 2}, {"marca": "VITINA", "id": "7790070318893", "precioMax": 17.49, "precioMin": 17.49, "nombre": "Semola Plus Espinaca Caja Lucchetti Nutri Vitina x 250 Gr", "presentacion": "250.0 gr", "cantSucursalesDisponible": 2}, {"marca": "MAMA COCINA", "id": "7792180006769", "precioMax": 26.99, "precioMin": 26.99, "nombre": "Premez N\u0303oquis Esp M Cocin", "presentacion": "400.0 gr", "cantSucursalesDisponible": 2}, {"marca": "VITINA", "id": "7790070318909", "precioMax": 17.49, "precioMin": 17.49, "nombre": "Semola Vegetales Caja Vitina Lucchetti x 250 Gr", "presentacion": "250.0 gr", "cantSucursalesDisponible": 2}, {"marca": "MAMA COCINA", "id": "7792180006752", "precioMax": 26.99, "precioMin": 26.99, "nombre": "Premezcla N\u0303oquis Mc Plus", "presentacion": "400.0 gr", "cantSucursalesDisponible": 2}, {"marca": "EGRAN", "id": "7791476070002", "precioMax": 16.49, "precioMin": 16.49, "nombre": "Semola Egran Candeal x 400 Gr", "presentacion": "400.0 gr", "cantSucursalesDisponible": 2}, {"marca": "COTO", "id": "12-1-2800002552143", "precioMax": 22.99, "precioMin": 22.99, "nombre": "Almidon de Maiz Coto Caja x 500 Gr", "presentacion": "500.0 gr", "cantSucursalesDisponible": 2}, {"marca": "BARBARA", "id": "7794270035512", "precioMax": 8.6, "precioMin": 8.6, "nombre": "Harina Barbara 000 x 1 Kg", "presentacion": "1.0 kg", "cantSucursalesDisponible": 1}, {"marca": "GREAT VALUE", "id": "0681131411257", "precioMax": 16.6, "precioMin": 16.6, "nombre": "Harina Maiz Grate Value x 1 Kg", "presentacion": "1000.0 kg", "cantSucursalesDisponible": 1}, {"marca": "LA ESQUINA DE LAS FLORES", "id": "7793132005403", "precioMax": 36.99, "precioMin": 36.99, "nombre": "Harina de Trigo Intantaneo Super Fina La Esquina de Las Florres x 1 Kg", "presentacion": "1.0 kg", "cantSucursalesDisponible": 1}, {"marca": "MAIZENA", "id": "7794000599178", "precioMax": 14.89, "precioMin": 14.89, "nombre": "Almidon de Maiz Maizena Bolsa x 215 Gr", "presentacion": "215.0 gr", "cantSucursalesDisponible": 1}, {"marca": "BARBARA", "id": "7794270035529", "precioMax": 10.7, "precioMin": 10.7, "nombre": "Harina Barbara de Trigo 0000 x 1 Kg", "presentacion": "1.0 kg", "cantSucursalesDisponible": 1}, {"marca": "EGRAN", "id": "7791476036008", "precioMax": 16.99, "precioMin": 16.99, "nombre": "Maiz Pisingallo Egran x 500 Gr", "presentacion": "500.0 gr", "cantSucursalesDisponible": 1}, {"marca": "GREAT VALUE", "id": "7798153719230", "precioMax": 11.7, "precioMin": 11.7, "nombre": "Harina 0000 Great Value 0000 Erduma x 1 Kg", "presentacion": "1.0 kg", "cantSucursalesDisponible": 1}, {"marca": "GREAT VALUE", "id": "7798153719247", "precioMax": 8.3, "precioMin": 8.3, "nombre": "Harina 000 Great Value 000 Erduma x 1 Kg", "presentacion": "1.0 kg", "cantSucursalesDisponible": 1}], "totalPagina": 81}